bendevlib/__init__.py
bendevlib-1.0.0.dist-info/licenses/LICENSE
bendevlib-1.0.0.dist-info/METADATA
bendevlib-1.0.0.dist-info/WHEEL
bendevlib-1.0.0.dist-info/top_level.txt
bendevlib-1.0.0.dist-info/RECORD
